README.rst
setup.py
devices/__init__.py
devices/utility.py
devices/provider/__init__.py
devices/provider/devices.py
devices/provider/test.py
devices/provider/utility.py
flask_oauth2_devices.egg-info/PKG-INFO
flask_oauth2_devices.egg-info/SOURCES.txt
flask_oauth2_devices.egg-info/dependency_links.txt
flask_oauth2_devices.egg-info/requires.txt
flask_oauth2_devices.egg-info/top_level.txt