Metadata-Version: 1.1
Name: flask-oauth2-devices
Version: 0.0.1
Summary: OAuth2 for devices flow implementation for Flask
Home-page: https://github.com/greedo/flask-oauth2-devices
Author: Joe Cabrera
Author-email: jcabrera@eminorlabs.com
License: MIT License
Keywords: Flask,
Platform: UNKNOWN
Classifier: Development Status :: 4 - Beta
Classifier: Environment :: Web Environment
Classifier: Intended Audience :: Developers
Classifier: License :: OSI Approved
Classifier: License :: OSI Approved :: MIT License
Classifier: Operating System :: OS Independent
Classifier: Natural Language :: English
Classifier: Programming Language :: Python :: 2.7
Classifier: Programming Language :: Python :: Implementation
Classifier: Programming Language :: Python :: Implementation :: CPython
Classifier: Programming Language :: Python :: Implementation :: PyPy
Classifier: Topic :: Internet :: WWW/HTTP :: Dynamic Content
Classifier: Topic :: Software Development :: Libraries :: Python Modules
